zach_test_tool/__init__.py
zach_test_tool/math/__init__.py
zach_test_tool/math/basic.py
zach_test_tool/web/__init__.py
zach_test_tool/web/client.py
zach_test_tool-0.1.0.dist-info/METADATA
zach_test_tool-0.1.0.dist-info/WHEEL
zach_test_tool-0.1.0.dist-info/RECORD
